asciimatics_overlay_ov/__init__.py
asciimatics_overlay_ov/__main__.py
asciimatics_overlay_ov/asciimatics_overlay_main.py
asciimatics_overlay_ov/colour_class.py
asciimatics_overlay_ov/display_class.py
asciimatics_overlay_ov/get_class.py
asciimatics_overlay_ov/is_class.py
asciimatics_overlay_ov/screen_class.py
asciimatics_overlay_ov/example_scripts/__init__.py
asciimatics_overlay_ov/example_scripts/checkboxes.py
asciimatics_overlay_ov/example_scripts/chess_test.py
asciimatics_overlay_ov/example_scripts/close_without_raising.py
asciimatics_overlay_ov/example_scripts/date_and_time_picker.py
asciimatics_overlay_ov/example_scripts/file_browser.py
asciimatics_overlay_ov/example_scripts/hello_world.py
asciimatics_overlay_ov/example_scripts/inut_field.py
asciimatics_overlay_ov/example_scripts/list_data.py
asciimatics_overlay_ov/example_scripts/list_fields.py
asciimatics_overlay_ov/example_scripts/non_window_hello_world.py
asciimatics_overlay_ov/example_scripts/popup.py
asciimatics_overlay_ov/example_scripts/radiobuttons.py
asciimatics_overlay_ov/example_scripts/test_menu_input.py
asciimatics_overlay_ov/widgets/__init__.py
asciimatics_overlay_ov/widgets/frame_nodes/__init__.py
asciimatics_overlay_ov/widgets/frame_nodes/frame_nodes.py
tests/__init__.py
tests/test_asciimatics_overlay_ov.py
asciimatics_overlay_ov-1.0.10.dist-info/LICENSE
asciimatics_overlay_ov-1.0.10.dist-info/METADATA
asciimatics_overlay_ov-1.0.10.dist-info/WHEEL
asciimatics_overlay_ov-1.0.10.dist-info/top_level.txt
asciimatics_overlay_ov-1.0.10.dist-info/RECORD
