Metadata-Version: 2.1
Name: asciimatics_overlay_ov
Version: 1.0.10
Summary: A module that help speed up some elements in using asciimatics
Home-page: https://github.com/Hanra-s-work/asciimatics_overlay_ov
Author: Henry Letellier
Author-email: henrysoftwarehouse@protonmail.com
Classifier: Programming Language :: Python :: 3
Classifier: License :: OSI Approved :: MIT License
Classifier: Operating System :: OS Independent
License-File: LICENSE
Requires-Dist: asciimatics==1.15.0
Requires-Dist: english-words==2.0.1
Requires-Dist: python-magic==0.4.27
